MANIFEST.in
README.rst
setup.py
egghatch/__init__.py
egghatch/block.py
egghatch/main.py
egghatch/misc.py
egghatch/shellcode.py
egghatch.egg-info/PKG-INFO
egghatch.egg-info/SOURCES.txt
egghatch.egg-info/dependency_links.txt
egghatch.egg-info/entry_points.txt
egghatch.egg-info/requires.txt
egghatch.egg-info/top_level.txt