Metadata-Version: 1.1
Name: egghatch
Version: 0.2.2
Summary: Cuckoo Sandbox Shellcode Identification & Formatting
Home-page: https://cuckoosandbox.org/
Author: Jurriaan Bremer
Author-email: jbr@cuckoo.sh
License: GPLv3
Platform: UNKNOWN
Classifier: Development Status :: 4 - Beta
Classifier: Environment :: Console
Classifier: Environment :: Web Environment
Classifier: Framework :: Pytest
Classifier: Intended Audience :: Information Technology
Classifier: Intended Audience :: Science/Research
Classifier: Natural Language :: English
Classifier: License :: OSI Approved :: GNU General Public License v3 (GPLv3)
Classifier: Operating System :: POSIX :: Linux
Classifier: Programming Language :: Python :: 2.7
Classifier: Topic :: Security
